[
    {
        "code": "CS 201",
        "name": "Theory of Computing",
        "instructor": "Prof. Bireswar Das",
        "semester": "Even",
        "schedule": "Monday, Wednesday - 10 am",
        "classroom": "10/202",
        "prerequisites": "ES 112",
        "grading": "50% Lab, 50% Exam",
        "description": ""
    },
    {
        "code": "CS 202",
        "name": "Software Tools and Techniques",
        "instructor": "Prof. Shouvick Mondal",
        "semester": "Even",
        "schedule": "Monday, Wednesday - 10 am",
        "classroom": "10/202",
        "prerequisites": "ES 112",
        "grading": "50% Lab, 50% Exam",
        "description": ""
    },
    {
        "code": "CS 303",
        "name": "Mathematical Foundations for AI",
        "instructor": "Prof. Neeldhara Misra",
        "semester": "Even",
        "schedule": "Monday, Wednesday - 2 pm",
        "classroom": "10/202",
        "prerequisites": "ES 112",
        "grading": "50% Quizzes, 50% Exam",
        "description": ""
    },
    {
        "code": "ES 301",
        "name": "Data Structures and Algorithms II",
        "instructor": "Prof. Manoj Gupta",
        "semester": "Even",
        "schedule": "Monday, Wednesday - 5 pm",
        "classroom": "10/103",
        "prerequisites": "ES 112, ES 242",
        "grading": "25% Quizzes, 75% Exam",
        "description": ""
    },
    {
        "code": "CS 330",
        "name": "Operating Systems",
        "instructor": "Prof. Abhishek Bicchawat",
        "semester": "Even",
        "schedule": "Monday, Wednesday - 5 pm",
        "classroom": "10/202",
        "prerequisites": "ES 112",
        "grading": "50% Quizzes, 50% Exam",
        "description": ""
    }
]